{
	"supervisior": [
		{ "menu": "/mesin", "permission": "CRUD" },
		{ "menu": "/hasil-perbaikan", "permission": "R" },
		{ "menu": "/teknisi", "permission": "CRUD" },
		{ "menu": "/biodata", "permission": "CRUD" }
	],
	"leader": [
		{ "menu": "/perbaikan", "permission": "CRUD" },
		{ "menu": "/hasil-perbaikan", "permission": "R" },
		{ "menu": "/teknisi", "permission": "R" },
		{ "menu": "/biodata", "permission": "CRUD" }
	],
	"produksi": [
		{ "menu": "/mesin", "permission": "R" },
		{ "menu": "/perbaikan", "permission": "CRUD" },
		{ "menu": "/biodata", "permission": "CRUD" }
	],
	"teknisi": [
		{ "menu": "/absensi", "permission": "C" },
		{ "menu": "/perbaikan", "permission": "CRUD" },
		{ "menu": "/biodata", "permission": "CRUD" }
	]
}
